vertica_sqlalchemy_dialect/__init__.py
vertica_sqlalchemy_dialect/base.py
vertica_sqlalchemy_dialect/dialect_pyodbc.py
vertica_sqlalchemy_dialect/dialect_vertica_python.py
vertica_sqlalchemy_dialect/requirements.py
vertica_sqlalchemy_dialect-0.0.8.2.dist-info/LICENSE
vertica_sqlalchemy_dialect-0.0.8.2.dist-info/METADATA
vertica_sqlalchemy_dialect-0.0.8.2.dist-info/WHEEL
vertica_sqlalchemy_dialect-0.0.8.2.dist-info/entry_points.txt
vertica_sqlalchemy_dialect-0.0.8.2.dist-info/top_level.txt
vertica_sqlalchemy_dialect-0.0.8.2.dist-info/RECORD
