Metadata-Version: 2.1
Name: vertica-sqlalchemy-dialect
Version: 0.0.8.2
Summary: Official Vertica dialect for SQLalchemy
Home-page: https://github.com/vertica/vertica-sqlalchemy-dialect
Author: Narendra Prabhu
License: Apache License 2.0
License-File: LICENSE
Requires-Dist: six >=1.10.0
Requires-Dist: sqlalchemy <=1.4.44,>=1.3.24
Requires-Dist: vertica-python >=1.1.1
Provides-Extra: pyodbc
Requires-Dist: pyodbc >=4.0.16 ; extra == 'pyodbc'
Provides-Extra: vertica-python
Requires-Dist: vertica-python >=1.1.1 ; extra == 'vertica-python'
